{
  "abs_tol": "1e-140",
  "all_cache_A_radius_contains_A_ball": null,
  "cache_checks": 0,
  "cutoff": "8",
  "dps": 220,
  "elapsed_seconds_total": 7.5701578999869525,
  "k_max": 55,
  "k_min": 54,
  "kind": "acb_coefficient_enclosure_summary",
  "lambdas": [
    "0.1"
  ],
  "max_A_radius": {
    "k": 54,
    "lam": "0.1",
    "log10_radius": "-242.617574294041447066928354655",
    "radius": "2.412268834437948823492870371657786602679e-243"
  },
  "max_c_radius": {
    "k": 54,
    "lam": "0.1",
    "log10_radius": "-313.980892318116465792263772455",
    "radius": "1.04497928626746447022798824543844232809e-314"
  },
  "n_sum": 100,
  "rows": 2
}
