{
  "checker": "work/rh_compute/scripts/check_jensen_window_pf_negative_lambda_relative_gaussian_degree16_collar_scan.py",
  "date": "2026-07-07",
  "generator": "work/rh_compute/scripts/jensen_window_pf_negative_lambda_relative_gaussian_degree16_collar_scan.py",
  "invariants": [
    "No row is ready_to_apply.",
    "Integer-T scan thresholds are not promoted to analytic collar theorems.",
    "Pointwise budget failure on the scan is not promoted to failure of a direct stencil-tail theorem.",
    "The scan is k=22 and degree-16 specific.",
    "Endpoint PF, RH, Laguerre-Polya membership, and Lambda <= 0 are forbidden as inputs."
  ],
  "kind": "jensen_window_pf_negative_lambda_relative_gaussian_degree16_collar_scan",
  "matrix_rows": [
    {
      "claim": "The degree-16 continuation is scanned on every integer T in the stated collar range for the M=7 to M=8 relative-Gaussian stencil.",
      "diagnostics": {
        "baseline_positive_rows": 1283,
        "continuation_positive_rows": 1045,
        "first_baseline_positive": {
          "T": "918",
          "baseline_positive": true,
          "companion_margin_M7": "7.262074730974056786E-6",
          "companion_margin_M8": "-2.050642156236996565E-6",
          "continuation_positive": false,
          "half_safety_stencils_satisfied": false,
          "pointwise_budget_satisfied": false,
          "pointwise_over_budget": "2.638097770251728679E+5",
          "q_over_T": "2.450980392156862745E-2",
          "weighted_gap_margin_M7": "1.371533618897523357E-6",
          "weighted_gap_margin_M8": "4.957708333301017479E-4",
          "worst_stencil_abs_over_half_margin": "7.209437565352806308E+2"
        },
        "first_continuation_positive": {
          "T": "1156",
          "baseline_positive": true,
          "companion_margin_M7": "1.076901687319863147E-6",
          "companion_margin_M8": "8.851471227548859301E-10",
          "continuation_positive": true,
          "half_safety_stencils_satisfied": false,
          "pointwise_budget_satisfied": false,
          "pointwise_over_budget": "9.265358648833857778E+2",
          "q_over_T": "1.946366782006920415E-2",
          "weighted_gap_margin_M7": "1.943811268953516069E-4",
          "weighted_gap_margin_M8": "2.518416978813492713E-4",
          "worst_stencil_abs_over_half_margin": "1.998356122693134981E+0"
        },
        "first_half_safety": {
          "T": "1483",
          "baseline_positive": true,
          "companion_margin_M7": "2.247804045125214229E-7",
          "companion_margin_M8": "1.124347089699779384E-7",
          "continuation_positive": true,
          "half_safety_stencils_satisfied": true,
          "pointwise_budget_satisfied": false,
          "pointwise_over_budget": "5.026186238681315692E+2",
          "q_over_T": "1.517194875252865813E-2",
          "weighted_gap_margin_M7": "1.450104075570647533E-4",
          "weighted_gap_margin_M8": "1.510418603694484371E-4",
          "worst_stencil_abs_over_half_margin": "9.996039982772186202E-1"
        },
        "half_safety_rows": 718,
        "parameters": {
          "baseline_M": 7,
          "coefficient_max_taylor_degree": 16,
          "continuation_M": 8,
          "precision_bits": 256,
          "scan_end_T": 2200,
          "scan_start_T": 900,
          "tail_cutoff_n": 80,
          "tail_start_k": 22
        },
        "pointwise_budget_failure_rows": 1283,
        "pointwise_budget_success_rows": 0,
        "scan_rows": 1301,
        "selected_rows": [
          {
            "T": "900",
            "baseline_positive": false,
            "companion_margin_M7": "8.663715483434626816E-6",
            "companion_margin_M8": "-2.585087157631684242E-6",
            "continuation_positive": false,
            "half_safety_stencils_satisfied": false,
            "pointwise_budget_satisfied": null,
            "pointwise_over_budget": null,
            "q_over_T": "2.500000000000000000E-2",
            "weighted_gap_margin_M7": "-5.850419445657931068E-5",
            "weighted_gap_margin_M8": "5.383536975387089451E-4",
            "worst_stencil_abs_over_half_margin": null
          },
          {
            "T": "950",
            "baseline_positive": true,
            "companion_margin_M7": "5.370493572779656131E-6",
            "companion_margin_M8": "-1.355197819587097835E-6",
            "continuation_positive": false,
            "half_safety_stencils_satisfied": false,
            "pointwise_budget_satisfied": false,
            "pointwise_over_budget": "3.405872159129435525E+3",
            "q_over_T": "2.368421052631578947E-2",
            "weighted_gap_margin_M7": "7.789148147073716834E-5",
            "weighted_gap_margin_M8": "4.352810148466106944E-4",
            "worst_stencil_abs_over_half_margin": "9.176601256714835882E+0"
          },
          {
            "T": "1000",
            "baseline_positive": true,
            "companion_margin_M7": "3.452036730520413111E-6",
            "companion_margin_M8": "-6.930385931843005222E-7",
            "continuation_positive": false,
            "half_safety_stencils_satisfied": false,
            "pointwise_budget_satisfied": false,
            "pointwise_over_budget": "1.139255507841004152E+3",
            "q_over_T": "2.250000000000000000E-2",
            "weighted_gap_margin_M7": "1.466754393862739616E-4",
            "weighted_gap_margin_M8": "3.672349168521610482E-4",
            "worst_stencil_abs_over_half_margin": "3.007449350603783080E+0"
          },
          {
            "T": "1100",
            "baseline_positive": true,
            "companion_margin_M7": "1.578707227607150820E-6",
            "companion_margin_M8": "-1.238943873083390585E-7",
            "continuation_positive": false,
            "half_safety_stencils_satisfied": false,
            "pointwise_budget_satisfied": false,
            "pointwise_over_budget": "9.817172108054247579E+2",
            "q_over_T": "2.045454545454545455E-2",
            "weighted_gap_margin_M7": "1.923099821980168213E-4",
            "weighted_gap_margin_M8": "2.831230178557149462E-4",
            "worst_stencil_abs_over_half_margin": "2.156956762016128840E+0"
          },
          {
            "T": "1153",
            "baseline_positive": true,
            "companion_margin_M7": "1.098134959221804479E-6",
            "companion_margin_M8": "-3.950543371415399732E-9",
            "continuation_positive": false,
            "half_safety_stencils_satisfied": false,
            "pointwise_budget_satisfied": false,
            "pointwise_over_budget": "9.297515614256565428E+2",
            "q_over_T": "1.951431049436253252E-2",
            "weighted_gap_margin_M7": "1.944855117045181594E-4",
            "weighted_gap_margin_M8": "2.533346006074945900E-4",
            "worst_stencil_abs_over_half_margin": "2.007195005200845186E+0"
          },
          {
            "T": "1154",
            "baseline_positive": true,
            "companion_margin_M7": "1.090998041845947650E-6",
            "companion_margin_M8": "-2.319815056389729095E-9",
            "continuation_positive": false,
            "half_safety_stencils_satisfied": false,
            "pointwise_budget_satisfied": false,
            "pointwise_over_budget": "9.286827445420609807E+2",
            "q_over_T": "1.949740034662045061E-2",
            "weighted_gap_margin_M7": "1.944528560626959271E-4",
            "weighted_gap_margin_M8": "2.528349616498292444E-4",
            "worst_stencil_abs_over_half_margin": "2.004252647516148877E+0"
          },
          {
            "T": "1155",
            "baseline_positive": true,
            "companion_margin_M7": "1.083920473319591554E-6",
            "companion_margin_M8": "-7.079873820087283923E-10",
            "continuation_positive": false,
            "half_safety_stencils_satisfied": false,
            "pointwise_budget_satisfied": false,
            "pointwise_over_budget": "9.276108418590771923E+2",
            "q_over_T": "1.948051948051948052E-2",
            "weighted_gap_margin_M7": "1.944180521919304074E-4",
            "weighted_gap_margin_M8": "2.523373321469098035E-4",
            "worst_stencil_abs_over_half_margin": "2.001306345621169903E+0"
          },
          {
            "T": "1156",
            "baseline_positive": true,
            "companion_margin_M7": "1.076901687319863147E-6",
            "companion_margin_M8": "8.851471227548859301E-10",
            "continuation_positive": true,
            "half_safety_stencils_satisfied": false,
            "pointwise_budget_satisfied": false,
            "pointwise_over_budget": "9.265358648833857778E+2",
            "q_over_T": "1.946366782006920415E-2",
            "weighted_gap_margin_M7": "1.943811268953516069E-4",
            "weighted_gap_margin_M8": "2.518416978813492713E-4",
            "worst_stencil_abs_over_half_margin": "1.998356122693134981E+0"
          },
          {
            "T": "1157",
            "baseline_positive": true,
            "companion_margin_M7": "1.069941123515363743E-6",
            "companion_margin_M8": "2.459793526702945523E-9",
            "continuation_positive": true,
            "half_safety_stencils_satisfied": false,
            "pointwise_budget_satisfied": false,
            "pointwise_over_budget": "9.254578252159046767E+2",
            "q_over_T": "1.944684528954191876E-2",
            "weighted_gap_margin_M7": "1.943421066716090641E-4",
            "weighted_gap_margin_M8": "2.513480447752841385E-4",
            "worst_stencil_abs_over_half_margin": "1.995402002086580002E+0"
          },
          {
            "T": "1158",
            "baseline_positive": true,
            "companion_margin_M7": "1.063038227496939756E-6",
            "companion_margin_M8": "4.016154526233547062E-9",
            "continuation_positive": true,
            "half_safety_stencils_satisfied": false,
            "pointwise_budget_satisfied": false,
            "pointwise_over_budget": "9.243767345513813164E+2",
            "q_over_T": "1.943005181347150259E-2",
            "weighted_gap_margin_M7": "1.943010177184731211E-4",
            "weighted_gap_margin_M8": "2.508563588887468845E-4",
            "worst_stencil_abs_over_half_margin": "1.992444007332285501E+0"
          },
          {
            "T": "1200",
            "baseline_positive": true,
            "companion_margin_M7": "8.186441121134420616E-7",
            "companion_margin_M8": "5.523957637225961793E-8",
            "continuation_positive": true,
            "half_safety_stencils_satisfied": false,
            "pointwise_budget_satisfied": false,
            "pointwise_over_budget": "8.763841048399702086E+2",
            "q_over_T": "1.875000000000000000E-2",
            "weighted_gap_margin_M7": "1.910138376911800746E-4",
            "weighted_gap_margin_M8": "2.318158543664976342E-4",
            "worst_stencil_abs_over_half_margin": "1.865046176830977078E+0"
          },
          {
            "T": "1400",
            "baseline_positive": true,
            "companion_margin_M7": "3.051123640009925129E-7",
            "companion_margin_M8": "1.167906699005006557E-7",
            "continuation_positive": true,
            "half_safety_stencils_satisfied": false,
            "pointwise_budget_satisfied": false,
            "pointwise_over_budget": "6.101718429387744694E+2",
            "q_over_T": "1.607142857142857143E-2",
            "weighted_gap_margin_M7": "1.589345581805234348E-4",
            "weighted_gap_margin_M8": "1.690333664807173359E-4",
            "worst_stencil_abs_over_half_margin": "1.234441578381132124E+0"
          },
          {
            "T": "1480",
            "baseline_positive": true,
            "companion_margin_M7": "2.270799778728506394E-7",
            "companion_margin_M8": "1.126814727964722694E-7",
            "continuation_positive": true,
            "half_safety_stencils_satisfied": false,
            "pointwise_budget_satisfied": false,
            "pointwise_over_budget": "5.063230620944794051E+2",
            "q_over_T": "1.520270270270270270E-2",
            "weighted_gap_margin_M7": "1.454954061028646607E-4",
            "weighted_gap_margin_M8": "1.516368261888900678E-4",
            "worst_stencil_abs_over_half_margin": "1.007561354796623778E+0"
          },
          {
            "T": "1481",
            "baseline_positive": true,
            "companion_margin_M7": "2.263093260564225467E-7",
            "companion_margin_M8": "1.125997379393203429E-7",
            "continuation_positive": true,
            "half_safety_stencils_satisfied": false,
            "pointwise_budget_satisfied": false,
            "pointwise_over_budget": "5.050864812623714921E+2",
            "q_over_T": "1.519243754220121540E-2",
            "weighted_gap_margin_M7": "1.453335684143683193E-4",
            "weighted_gap_margin_M8": "1.514380843190536180E-4",
            "worst_stencil_abs_over_half_margin": "1.004904129216067558E+0"
          },
          {
            "T": "1482",
            "baseline_positive": true,
            "companion_margin_M7": "2.255428110132049839E-7",
            "companion_margin_M8": "1.125174810934742418E-7",
            "continuation_positive": true,
            "half_safety_stencils_satisfied": false,
            "pointwise_budget_satisfied": false,
            "pointwise_over_budget": "5.038516660425956902E+2",
            "q_over_T": "1.518218623481781377E-2",
            "weighted_gap_margin_M7": "1.451719020669568286E-4",
            "weighted_gap_margin_M8": "1.512397628351518590E-4",
            "worst_stencil_abs_over_half_margin": "1.002251673746439061E+0"
          },
          {
            "T": "1483",
            "baseline_positive": true,
            "companion_margin_M7": "2.247804045125214229E-7",
            "companion_margin_M8": "1.124347089699779384E-7",
            "continuation_positive": true,
            "half_safety_stencils_satisfied": true,
            "pointwise_budget_satisfied": false,
            "pointwise_over_budget": "5.026186238681315692E+2",
            "q_over_T": "1.517194875252865813E-2",
            "weighted_gap_margin_M7": "1.450104075570647533E-4",
            "weighted_gap_margin_M8": "1.510418603694484371E-4",
            "worst_stencil_abs_over_half_margin": "9.996039982772186202E-1"
          },
          {
            "T": "1484",
            "baseline_positive": true,
            "companion_margin_M7": "2.240220785457386871E-7",
            "companion_margin_M8": "1.123514282141585092E-7",
            "continuation_positive": true,
            "half_safety_stencils_satisfied": true,
            "pointwise_budget_satisfied": false,
            "pointwise_over_budget": "5.013873620969984849E+2",
            "q_over_T": "1.516172506738544474E-2",
            "weighted_gap_margin_M7": "1.448490853725367084E-4",
            "weighted_gap_margin_M8": "1.508443755609399430E-4",
            "worst_stencil_abs_over_half_margin": "9.969611125519517198E-1"
          },
          {
            "T": "1485",
            "baseline_positive": true,
            "companion_margin_M7": "2.232678053243309970E-7",
            "companion_margin_M8": "1.122676454062708496E-7",
            "continuation_positive": true,
            "half_safety_stencils_satisfied": true,
            "pointwise_budget_satisfied": false,
            "pointwise_over_budget": "5.001578880123863005E+2",
            "q_over_T": "1.515151515151515152E-2",
            "weighted_gap_margin_M7": "1.446879359927179401E-4",
            "weighted_gap_margin_M8": "1.506473070553093278E-4",
            "worst_stencil_abs_over_half_margin": "9.943230261686431520E-1"
          },
          {
            "T": "1600",
            "baseline_positive": true,
            "companion_margin_M7": "1.577225254174503579E-7",
            "companion_margin_M8": "1.005934937316762764E-7",
            "continuation_positive": true,
            "half_safety_stencils_satisfied": true,
            "pointwise_budget_satisfied": false,
            "pointwise_over_budget": "3.720472562250244587E+2",
            "q_over_T": "1.406250000000000000E-2",
            "weighted_gap_margin_M7": "1.273815096820546421E-4",
            "weighted_gap_margin_M8": "1.304529457317573060E-4",
            "worst_stencil_abs_over_half_margin": "7.244245111415562958E-1"
          },
          {
            "T": "1800",
            "baseline_positive": true,
            "companion_margin_M7": "9.941453330469274220E-8",
            "companion_margin_M8": "7.920154197169507982E-8",
            "continuation_positive": true,
            "half_safety_stencils_satisfied": true,
            "pointwise_budget_satisfied": false,
            "pointwise_over_budget": "2.151886648409221180E+2",
            "q_over_T": "1.250000000000000000E-2",
            "weighted_gap_margin_M7": "1.030280803948506441E-4",
            "weighted_gap_margin_M8": "1.041170141427360220E-4",
            "worst_stencil_abs_over_half_margin": "4.066405717773164399E-1"
          },
          {
            "T": "2000",
            "baseline_positive": true,
            "companion_margin_M7": "6.996640552097379494E-8",
            "companion_margin_M8": "6.191220017299330373E-8",
            "continuation_positive": true,
            "half_safety_stencils_satisfied": true,
            "pointwise_budget_satisfied": false,
            "pointwise_over_budget": "1.248008080287443688E+2",
            "q_over_T": "1.125000000000000000E-2",
            "weighted_gap_margin_M7": "8.470067565765344792E-5",
            "weighted_gap_margin_M8": "8.513530052272832770E-5",
            "worst_stencil_abs_over_half_margin": "2.302306453506772200E-1"
          },
          {
            "T": "2200",
            "baseline_positive": true,
            "companion_margin_M7": "5.242476474904102008E-8",
            "companion_margin_M8": "4.889720300717582147E-8",
            "continuation_positive": true,
            "half_safety_stencils_satisfied": true,
            "pointwise_budget_satisfied": false,
            "pointwise_over_budget": "7.440371789203736033E+1",
            "q_over_T": "1.022727272727272727E-2",
            "weighted_gap_margin_M7": "7.075945919021972045E-5",
            "weighted_gap_margin_M8": "7.095007736307137735E-5",
            "worst_stencil_abs_over_half_margin": "1.345761591397404041E-1"
          }
        ],
        "worst_pointwise_over_budget": {
          "T": "918",
          "sample": "2.638097770251728679E+5"
        },
        "worst_stencil_abs_over_half_margin": {
          "T": "918",
          "sample": "7.209437565352806308E+2"
        }
      },
      "id": "nlrgd16cs_01_integer_T_scan",
      "proof_boundary": "Finite integer-grid scan only; not an analytic collar theorem.",
      "readiness": "not_ready_to_apply",
      "role": "finite_diagnostic",
      "source_artifacts": [
        "outputs/jensen_window_pf_negative_lambda_relative_gaussian_degree16_stencil_continuation.md"
      ]
    },
    {
      "claim": "On the scanned integer grid, the degree-14 baseline first has all three positive stencils at T=918.",
      "id": "nlrgd16cs_02_baseline_threshold",
      "proof_boundary": "Finite threshold only; not a statement for all real T or all k.",
      "readiness": "not_ready_to_apply",
      "role": "finite_threshold"
    },
    {
      "claim": "On the scanned integer grid, the degree-16 continuation first preserves all three structured stencil signs at T=1156.",
      "id": "nlrgd16cs_03_continuation_threshold",
      "proof_boundary": "Finite threshold only; not an infinite Taylor-tail theorem.",
      "readiness": "not_ready_to_apply",
      "role": "finite_threshold"
    },
    {
      "claim": "On the scanned integer grid, the stricter half-safety stencil-increment condition first holds at T=1483.",
      "id": "nlrgd16cs_04_half_safety_threshold",
      "proof_boundary": "Finite sufficient-condition threshold only; not a proof outside the scan.",
      "readiness": "not_ready_to_apply",
      "role": "finite_threshold"
    },
    {
      "claim": "The crude pointwise half-safety budget fails for every baseline-positive row in the scanned collar range.",
      "id": "nlrgd16cs_05_pointwise_route_blocked_on_scan",
      "proof_boundary": "Finite obstruction to this pointwise shortcut only; not a disproof of sharper analytic estimates.",
      "readiness": "not_ready_to_apply",
      "role": "finite_obstruction"
    },
    {
      "claim": "A direct signed stencil-tail theorem should aim for an explicit large-T/q-over-T collar, with T=1156 as the first finite sign-survival threshold and T=1483 as the first finite half-safety threshold in this scan.",
      "id": "nlrgd16cs_06_live_collar_theorem_target",
      "proof_boundary": "Live theorem-search target only; no analytic collar theorem is proved.",
      "readiness": "not_ready_to_apply",
      "role": "live_route",
      "source_artifacts": [
        "outputs/jensen_window_pf_negative_lambda_uniform_remainder_target.md",
        "outputs/jensen_window_pf_negative_lambda_relative_gaussian_degree16_stencil_continuation.md"
      ]
    },
    {
      "claim": "The finite integer-T collar scan proves the required direct signed stencil-tail theorem.",
      "gap": "The scan is finite, k=22-specific, degree-16-specific, and does not bound the infinite residual Taylor tail.",
      "id": "nlrgd16cs_07_scan_promotion_rejected",
      "proof_boundary": "Rejected finite promotion only; not a proof of scaled-curvature monotonicity, cone entry, RH, or Lambda <= 0.",
      "readiness": "not_ready_to_apply",
      "role": "rejected_route"
    }
  ],
  "proof_boundary": "Finite theorem-search diagnostic only. It scans an integer T collar for k=22 and degree-16 continuation, but it does not prove a real-T collar theorem, does not prove an infinite Taylor-tail theorem, does not prove scaled-curvature monotonicity, does not prove cone entry, and does not prove RH or Lambda <= 0.",
  "source_degree16_continuation": "outputs/jensen_window_pf_negative_lambda_relative_gaussian_degree16_stencil_continuation.md",
  "source_dependency_graph": "outputs/signed_hankel_jensen_dependency_graph.md",
  "source_uniform_remainder_target": "outputs/jensen_window_pf_negative_lambda_uniform_remainder_target.md",
  "status": "finite theorem-search diagnostic",
  "summary": {
    "baseline_positive_rows": 1283,
    "continuation_positive_rows": 1045,
    "first_baseline_positive_T": "918",
    "first_continuation_positive_T": "1156",
    "first_continuation_q_over_T": "1.946366782006920415E-2",
    "first_half_safety_T": "1483",
    "first_half_safety_q_over_T": "1.517194875252865813E-2",
    "half_safety_rows": 718,
    "main_finding": "The degree-16 collar scan on T=900..2200 makes the large-T signal concrete: the M=7 baseline first has positive stencils at T=918, the M=8 continuation first preserves signs at T=1156 (q/T=1.946366782006920415E-2), and half-safety first holds at T=1483 (q/T=1.517194875252865813E-2). The crude pointwise budget fails on all baseline-positive rows, so the live route remains a direct signed stencil-tail collar theorem.",
    "matrix_rows": 7,
    "pointwise_budget_failure_rows": 1283,
    "pointwise_budget_success_rows": 0,
    "ready_to_apply_rows": 0,
    "scan_rows": 1301,
    "target_closing": false
  }
}
