{
  "abs_tol": "1e-150",
  "all_cache_A_radius_contains_A_ball": null,
  "cache_checks": 0,
  "cutoff": "7",
  "dps": 220,
  "elapsed_seconds_total": 2.519285900008981,
  "k_max": 326,
  "k_min": 325,
  "kind": "acb_coefficient_enclosure_summary",
  "lambdas": [
    "-100.0"
  ],
  "max_A_radius": {
    "k": 325,
    "lam": "-100.0",
    "log10_radius": "-1020.48383169655234582224510097",
    "radius": "3.282224655096762705927801491532570664673e-1021"
  },
  "max_c_radius": {
    "k": 325,
    "lam": "-100.0",
    "log10_radius": "-1697.35536037029859737238071921",
    "radius": "4.412041915577393315252269108732880818064e-1698"
  },
  "n_sum": 70,
  "rows": 2
}
